crudance/__init__.py
crudance/config/__init__.py
crudance/config/fields.py
crudance/controllers/__init__.py
crudance/controllers/getter.py
crudance/controllers/mapper.py
crudance/controllers/post.py
crudance/controllers/tools.py
crudance/helpers/__init__.py
crudance/helpers/exceptions.py
crudance/helpers/within_transaction.py
crudance/json_models/__init__.py
crudance/json_models/post.py
crudance/json_models/root.py
crud_templates-0.1.1.dist-info/LICENSE
crud_templates-0.1.1.dist-info/METADATA
crud_templates-0.1.1.dist-info/WHEEL
crud_templates-0.1.1.dist-info/top_level.txt
crud_templates-0.1.1.dist-info/RECORD
