Metadata-Version: 2.1
Name: crud-templates
Version: 0.1.1
Summary: Powerful yet discrete templates for CRUD controllers
Author-email: Romain Damian <damian.romain@gmail.com>
License: MIT License
License-File: LICENSE
Requires-Dist: marshmallow (>=3.0)
Requires-Dist: sqlalchemy (>=2.0)
